monk_lotto/__init__.py
monk_lotto/draw.py
monk_lotto-0.1.0.dist-info/METADATA
monk_lotto-0.1.0.dist-info/WHEEL
monk_lotto-0.1.0.dist-info/top_level.txt
monk_lotto-0.1.0.dist-info/RECORD
