Metadata-Version: 2.1
Name: monk_lotto
Version: 0.1.0
Summary: Default template for PDM package
Author-email: thephunkmonk <andrewchoi1218@gmail.com>
License: MIT
Requires-Python: ==3.11.*
